back_propagation
