Metadata-Version: 2.1
Name: BackPropagation2
Version: 0.0.2
Summary: Python Package for Back Propagation Implement
Home-page: https://github.com/Wingsgo/Back_Propagation
Author: WingC
Author-email: 1018957763@qq.com
License: MIT
Keywords: Machine_Learning Back_Propagation
Platform: UNKNOWN
Classifier: Development Status :: 3 - Alpha
Classifier: Intended Audience :: Developers
Classifier: License :: OSI Approved :: MIT License
Classifier: Programming Language :: Python :: 3
Provides-Extra: test
